Workbook
Name Slicer_City: #N/A
Name Slicer_Payment_Mode: #N/A

Sheet Raw Dataset
A1: Order_ID | B1: Order_Time | C1: City | D1: Restaurant | E1: Order_Value | F1: Delivery_Fee | G1: Discount | H1: Payment_Mode | I1: Delivery_Time_Min | J1: Final_Amount
A2: ORD100000 | B2: 44927 | C2: Kolkata | D2: Pizza Corner | E2: 1349.85 | F2: 21.28 | G2: 462.51 | H2: Card | I2: 45 | J2: 908.6199999999999
A3: ORD100001 | B3: 44927.042 | C3: Hyderabad | D3: South Express | E3: 528.88 | F3: 64.92 | G3: 233.45 | H3: Card | I3: 82 | J3: 360.34999999999997
A4: ORD100002 | B4: 44927.083 | C4: Chennai | D4: Pizza Corner | E4: 1590.35 | F4: 93.1 | G4: 326.73 | H4: Wallet | I4: 15 | J4: 1356.7199999999998
A5: ORD100003 | B5: 44927.125 | C5: Delhi | D5: South Express | E5: 1834.73 | F5: 72.82 | G5: 92.2 | H5: Card | I5: 57 | J5: 1815.35
A6: ORD100004 | B6: 44927.167 | C6: Mumbai | D6: Urban Tadka | E6: 1374.42 | F6: 50.05 | G6: 394.49 | H6: Cash | I6: 55 | J6: 1029.98
A7: ORD100005 | B7: 44927.208 | C7: Hyderabad | D7: Tandoori Nights | E7: 1935.57 | F7: 5.7 | G7: 365.14 | H7: Wallet | I7: 28 | J7: 1576.13
A8: ORD100006 | B8: 44927.25 | C8: Kolkata | D8: Tandoori Nights | E8: 944.53 | F8: 0.76 | G8: 372.22 | H8: UPI | I8: 85 | J8: 573.0699999999999
A9: ORD100007 | B9: 44927.292 | C9: Delhi | D9: Spice Hub | E9: 1208.05 | F9: 97.27 | G9: 137.99 | H9: UPI | I9: 48 | J9: 1167.33
A10: ORD100008 | B10: 44927.333 | C10: Delhi | D10: Urban Tadka | E10: 572.48 | F10: 23.16 | G10: 177.53 | H10: UPI | I10: 76 | J10: 418.11
A11: ORD100009 | B11: 44927.375 | C11: Mumbai | D11: Pizza Corner | E11: 551.64 | F11: 54.33 | G11: 308.42 | H11: UPI | I11: 13 | J11: 297.55
A12: ORD100010 | B12: 44927.417 | C12: Chennai | D12: South Express | E12: 483.8 | F12: 64.17 | G12: 352.64 | H12: Card | I12: 72 | J12: 195.33000000000004
A13: ORD100011 | B13: 44927.458 | C13: Kolkata | D13: Biryani House | E13: 1838.77 | F13: 21.35 | G13: 198.95 | H13: Cash | I13: 10 | J13: 1661.1699999999998
A14: ORD100012 | B14: 44927.5 | C14: Chennai | D14: Pizza Corner | E14: 886.72 | F14: 12.85 | G14: 26.19 | H14: Cash | I14: 82 | J14: 873.38
A15: ORD100013 | B15: 44927.542 | C15: Pune | D15: Urban Tadka | E15: 1043.69 | F15: 79.71 | G15: 356.89 | H15: Card | I15: 58 | J15: 766.5100000000001
A16: ORD100014 | B16: 44927.583 | C16: Mumbai | D16: Tandoori Nights | E16: 1920.18 | F16: 11.99 | G16: 68.19 | H16: UPI | I16: 45 | J16: 1863.98
A17: ORD100015 | B17: 44927.625 | D17: Biryani House | E17: 404.41 | F17: 32.97 | G17: 118.16 | H17: UPI | I17: 79 | J17: 319.22
A18: ORD100016 | B18: 44927.667 | C18: Chennai | D18: Pizza Corner | E18: 895.09 | F18: 21.67 | G18: 412.06 | H18: Wallet | I18: 10 | J18: 504.7
A19: ORD100017 | B19: 44927.708 | C19: Pune | D19: Tandoori Nights | E19: 1861.77 | F19: 12.5 | G19: 29.64 | H19: Cash | I19: 73 | J19: 1844.6299999999999
A20: ORD100018 | B20: 44927.75 | C20: Kolkata | D20: Spice Hub | E20: 1183.04 | F20: 71.24 | G20: 239.14 | H20: UPI | I20: 52 | J20: 1015.14
A21: ORD100019 | B21: 44927.792 | C21: Bangalore | D21: Urban Tadka | E21: 827.72 | F21: 73.55 | G21: 59.43 | H21: Cash | I21: 38 | J21: 841.84
A22: ORD100020 | B22: 44927.833 | C22: Chennai | D22: Tandoori Nights | E22: 1091.84 | F22: 82.62 | G22: 188.33 | H22: UPI | I22: 27 | J22: 986.13
A23: ORD100021 | B23: 44927.875 | C23: Hyderabad | D23: South Express | E23: 1972.65 | F23: 73.61 | G23: 335.02 | H23: UPI | I23: 40 | J23: 1711.24
A24: ORD100022 | B24: 44927.917 | C24: Chennai | D24: South Express | E24: 650.05 | F24: 85.15 | G24: 307.57 | H24: Wallet | I24: 37 | J24: 427.62999999999994
A25: ORD100023 | B25: 44927.958 | C25: Bangalore | D25: Urban Tadka | E25: 656.55 | F25: 41.64 | G25: 420.57 | H25: Card | I25: 81 | J25: 277.61999999999995
A26: ORD100024 | B26: 44928 | C26: Chennai | D26: Pizza Corner | E26: 1239.17 | F26: 90.46 | G26: 90.59 | H26: Card | I26: 12 | J26: 1239.0400000000002
A27: ORD100025 | B27: 44928.042 | C27: Kolkata | D27: South Express | E27: 1898.75 | F27: 10.28 | G27: 371.4 | H27: UPI | I27: 26 | J27: 1537.63
A28: ORD100026 | B28: 44928.083 | C28: Pune | D28: Pizza Corner | E28: 1879.83 | F28: 34.22 | G28: 441.52 | H28: Cash | I28: 54 | J28: 1472.53
A29: ORD100027 | B29: 44928.125 | C29: Bangalore | D29: South Express | E29: 1358.03 | F29: 24.87 | G29: 300.22 | H29: Card | I29: 19 | J29: 1082.6799999999998
A30: ORD100028 | B30: 44928.167 | C30: Chennai | D30: Urban Tadka | E30: 931.37 | F30: 1.31 | G30: 368.09 | H30: Cash | I30: 55 | J30: 564.5899999999999
A31: ORD100029 | B31: 44928.208 | C31: Mumbai | D31: Pizza Corner | E31: 796.86 | F31: 38.64 | G31: 464.24 | H31: Wallet | I31: 15 | J31: 371.26
A32: ORD100030 | B32: 44928.25 | C32: Mumbai | D32: Urban Tadka | E32: 1861.19 | F32: 54.93 | G32: 153.03 | H32: Cash | I32: 37 | J32: 1763.0900000000001
A33: ORD100031 | B33: 44928.292 | C33: Pune | D33: Biryani House | E33: 916.22 | F33: 61.65 | G33: 246.7 | H33: Card | I33: 48 | J33: 731.1700000000001
A34: ORD100032 | B34: 44928.333 | C34: Delhi | D34: Spice Hub | E34: 1747.22 | F34: 32.86 | G34: 363.05 | H34: Cash | I34: 81 | J34: 1417.03
A35: ORD100033 | B35: 44928.375 | C35: Pune | D35: South Express | E35: 1741.44 | F35: 84.4 | G35: 17.32 | H35: Cash | I35: 87 | J35: 1808.5200000000002
A36: ORD100034 | B36: 44928.417 | C36: Kolkata | D36: Urban Tadka | E36: 691.22 | F36: 75.47 | G36: 239.04 | H36: Cash | I36: 15 | J36: 527.6500000000001
A37: ORD100035 | B37: 44928.458 | C37: Mumbai | D37: Urban Tadka | E37: 1796.48 | F37: 69.19 | G37: 407.96 | H37: Wallet | I37: 25 | J37: 1457.71
A38: ORD100036 | B38: 44928.5 | C38: Mumbai | D38: Tandoori Nights | E38: 1527.5 | F38: 57.69 | G38: 164.33 | H38: Wallet | I38: 37 | J38: 1420.8600000000001
A39: ORD100037 | B39: 44928.542 | C39: Kolkata | D39: Urban Tadka | E39: 915.17 | F39: 4.02 | G39: 112.28 | H39: Card | I39: 58 | J39: 806.91
A40: ORD100038 | B40: 44928.583 | C40: Pune | D40: Biryani House | E40: 1123.85 | F40: 0.21 | G40: 192.29 | H40: UPI | I40: 38 | J40: 931.77
A41: ORD100039 | B41: 44928.625 | C41: Mumbai | D41: Spice Hub | E41: 1744.57 | F41: 8.27 | G41: 351.98 | H41: UPI | I41: 54 | J41: 1400.86
A42: ORD100040 | B42: 44928.667 | C42: Mumbai | D42: Biryani House | E42: 1181.02 | F42: 48.62 | G42: 409.19 | H42: Card | I42: 56 | J42: 820.4499999999998
A43: ORD100041 | B43: 44928.708 | C43: Delhi | D43: Biryani House | E43: 1335.92 | F43: 17.61 | G43: 178.68 | H43: UPI | I43: 77 | J43: 1174.85
A44: ORD100042 | B44: 44928.75 | C44: Chennai | D44: Biryani House | E44: 932.56 | F44: 57.38 | G44: 376.9 | H44: UPI | I44: 69 | J44: 613.04
A45: ORD100043 | B45: 44928.792 | C45: Mumbai | D45: Pizza Corner | F45: 21.79 | G45: 463.58 | H45: Wallet | I45: 36
A46: ORD100044 | B46: 44928.833 | C46: Delhi | D46: Spice Hub | E46: 1198.01 | F46: 72.52 | G46: 153.15 | H46: Cash | I46: 10 | J46: 1117.3799999999999
A47: ORD100045 | B47: 44928.875 | C47: Delhi | D47: Tandoori Nights | E47: 979.37 | F47: 71.91 | G47: 138.2 | H47: Cash | I47: 54 | J47: 913.0799999999999
A48: ORD100046 | B48: 44928.917 | C48: Kolkata | D48: Urban Tadka | E48: 586.39 | F48: 21.76 | G48: 87.74 | H48: UPI | I48: 48 | J48: 520.41
A49: ORD100047 | B49: 44928.958 | C49: Hyderabad | D49: Tandoori Nights | E49: 1994.19 | F49: 82.9 | G49: 270.77 | H49: UPI | I49: 69 | J49: 1806.3200000000002
A50: ORD100048 | B50: 44929 | C50: Bangalore | D50: South Express | E50: 291.86 | F50: 79.68 | G50: 388.68 | H50: UPI | I50: 54 | J50: -17.14
A51: ORD100049 | B51: 44929.042 | C51: Mumbai | D51: South Express | E51: 806.98 | F51: 78.3 | G51: 304.13 | H51: UPI | I51: 50 | J51: 581.15
A52: ORD100050 | B52: 44929.083 | C52: Delhi | D52: Spice Hub | E52: 1838.39 | F52: 53.36 | G52: 235.82 | H52: Card | I52: 25 | J52: 1655.93
A53: ORD100051 | B53: 44929.125 | C53: Pune | D53: Urban Tadka | E53: 1956.27 | F53: 39.12 | G53: 376.7 | H53: Cash | I53: 69 | J53: 1618.6899999999998
A54: ORD100052 | B54: 44929.167 | C54: Hyderabad | D54: South Express | E54: 149.31 | F54: 79.89 | G54: 205.7 | H54: Wallet | I54: 12 | J54: 23.5
A55: ORD100053 | B55: 44929.208 | C55: Pune | D55: Urban Tadka | E55: 1544.89 | F55: 99.88 | G55: 287.35 | H55: Card | I55: 24 | J55: 1357.42
A56: ORD100054 | B56: 44929.25 | C56: Kolkata | D56: Pizza Corner | E56: 685.19 | F56: 93 | G56: 221.81 | H56: Wallet | I56: 65 | J56: 556.3800000000001
A57: ORD100055 | B57: 44929.292 | C57: Mumbai | D57: Spice Hub | E57: 1389.68 | F57: 87.44 | G57: 154.46 | H57: Cash | I57: 20 | J57: 1322.66
A58: ORD100056 | B58: 44929.333 | C58: Mumbai | D58: South Express | E58: 1159.16 | F58: 39.07 | G58: 373.45 | H58: UPI | I58: 88 | J58: 824.78
A59: ORD100057 | B59: 44929.375 | C59: Hyderabad | D59: Pizza Corner | E59: 307.32 | F59: 83.33 | G59: 84.38 | H59: Cash | I59: 33 | J59: 306.27
A60: ORD100058 | B60: 44929.417 | C60: Chennai | D60: Tandoori Nights | E60: 173.49 | F60: 75.62 | G60: 375.8 | H60: Cash | I60: 61 | J60: -126.69
A61: ORD100059 | B61: 44929.458 | C61: Delhi | D61: South Express | E61: 1749.67 | F61: 4.59 | G61: 90.04 | H61: Wallet | I61: 56 | J61: 1664.22
A62: ORD100060 | B62: 44929.5 | C62: Mumbai | D62: Biryani House | E62: 1806.59 | F62: 96.45 | G62: 76.59 | H62: UPI | I62: 29 | J62: 1826.45
A63: ORD100061 | B63: 44929.542 | C63: Hyderabad | D63: Tandoori Nights | E63: 1995.73 | F63: 45.72 | G63: 314.98 | H63: Card | I63: 44 | J63: 1726.47
A64: ORD100062 | B64: 44929.583 | C64: Chennai | D64: South Express | E64: 1213.3 | F64: 51.69 | G64: 486.74 | H64: Cash | I64: 69 | J64: 778.25
A65: ORD100063 | B65: 44929.625 | C65: Bangalore | D65: Pizza Corner | E65: 991.06 | F65: 30.14 | G65: 219.71 | H65: UPI | I65: 56 | J65: 801.4899999999999
A66: ORD100064 | B66: 44929.667 | C66: Chennai | D66: South Express | E66: 1430.36 | F66: 39.84 | G66: 194.79 | H66: Cash | I66: 11 | J66: 1275.4099999999999
A67: ORD100065 | B67: 44929.708 | C67: Delhi | D67: Biryani House | E67: 1655.88 | F67: 73.41 | G67: 123.64 | H67: UPI | I67: 32 | J67: 1605.65
A68: ORD100066 | B68: 44929.75 | C68: Kolkata | D68: Pizza Corner | E68: 161.52 | F68: 63.52 | G68: 493.54 | H68: Cash | I68: 79 | J68: -268.5
A69: ORD100067 | B69: 44929.792 | C69: Hyderabad | D69: Tandoori Nights | E69: 360.68 | F69: 16.12 | G69: 234.66 | H69: Cash | I69: 20 | J69: 142.14000000000001
A70: ORD100068 | B70: 44929.833 | C70: Mumbai | D70: Pizza Corner | E70: 187.01 | F70: 76.49 | G70: 470.07 | H70: UPI | I70: 32 | J70: -206.57
A71: ORD100069 | B71: 44929.875 | C71: Bangalore | D71: Spice Hub | E71: 1149.79 | F71: 6.64 | G71: 339.58 | H71: Wallet | I71: 60 | J71: 816.8500000000001
A72: ORD100070 | B72: 44929.917 | C72: Delhi | D72: Biryani House | E72: 541.99 | F72: 57.06 | G72: 130.25 | H72: Wallet | I72: 23 | J72: 468.79999999999995
A73: ORD100071 | B73: 44929.958 | C73: Chennai | D73: South Express | E73: 1056.93 | F73: 32.69 | G73: 229.78 | H73: UPI | I73: 65 | J73: 859.8400000000001
A74: ORD100072 | B74: 44930 | C74: Mumbai | D74: Spice Hub | E74: 673.43 | F74: 85.73 | G74: 15.81 | H74: Card | I74: 69 | J74: 743.35
A75: ORD100073 | B75: 44930.042 | C75: Bangalore | D75: Tandoori Nights | E75: 1384.02 | F75: 71.52 | G75: 5.68 | H75: Wallet | I75: 21 | J75: 1449.86
A76: ORD100074 | B76: 44930.083 | C76: Bangalore | D76: Spice Hub | E76: 1200.32 | F76: 55.93 | G76: 67.33 | H76: Cash | I76: 67 | J76: 1188.92
A77: ORD100075 | B77: 44930.125 | C77: Mumbai | D77: Pizza Corner | E77: 1788.7 | F77: 63.44 | G77: 3.45 | H77: Card | I77: 64 | J77: 1848.69
A78: ORD100076 | B78: 44930.167 | C78: Delhi | D78: Biryani House | E78: 135.82 | F78: 98.08 | G78: 370.83 | H78: Wallet | I78: 47 | J78: -136.93
A79: ORD100077 | B79: 44930.208 | C79: Pune | D79: Tandoori Nights | E79: 1513.35 | F79: 58.16 | G79: 155.18 | H79: UPI | I79: 49 | J79: 1416.33
A80: ORD100078 | B80: 44930.25 | C80: Mumbai | D80: Spice Hub | E80: 1888.34 | F80: 5.85 | G80: 145.62 | H80: Cash | I80: 25 | J80: 1748.5699999999997
A81: ORD100079 | B81: 44930.292 | C81: Hyderabad | D81: Pizza Corner | E81: 1164.04 | F81: 49.11 | G81: 374.68 | H81: UPI | I81: 28 | J81: 838.4699999999998
A82: ORD100080 | B82: 44930.333 | C82: Pune | D82: Urban Tadka | E82: 1268.79 | F82: 24.37 | G82: 242.88 | H82: Wallet | I82: 48 | J82: 1050.2799999999997
A83: ORD100081 | B83: 44930.375 | C83: Kolkata | D83: Urban Tadka | E83: 1288.65 | F83: 44.81 | G83: 212.07 | H83: Wallet | I83: 50 | J83: 1121.39
A84: ORD100082 | B84: 44930.417 | C84: Chennai | D84: Urban Tadka | E84: 1041.1 | F84: 14.64 | G84: 35.33 | H84: UPI | I84: 44 | J84: 1020.41
A85: ORD100083 | B85: 44930.458 | C85: Hyderabad | D85: Biryani House | F85: 43.31 | G85: 172.09 | H85: UPI | I85: 60
A86: ORD100084 | B86: 44930.5 | C86: Kolkata | D86: Spice Hub | E86: 1781.62 | F86: 57.48 | G86: 87.67 | H86: Wallet | I86: 20 | J86: 1751.4299999999998
A87: ORD100085 | B87: 44930.542 | C87: Mumbai | D87: Urban Tadka | E87: 787.18 | F87: 52.06 | G87: 445.83 | H87: UPI | I87: 48 | J87: 393.41
A88: ORD100086 | B88: 44930.583 | C88: Hyderabad | D88: Tandoori Nights | E88: 1054.9 | F88: 43.11 | G88: 378.68 | H88: Wallet | I88: 13 | J88: 719.3299999999999
A89: ORD100087 | B89: 44930.625 | C89: Pune | D89: South Express | E89: 1481.89 | F89: 43.38 | G89: 465.66 | H89: Wallet | I89: 37 | J89: 1059.6100000000001
A90: ORD100088 | B90: 44930.667 | C90: Delhi | D90: Biryani House | E90: 252.31 | F90: 94.33 | G90: 297.47 | H90: Card | I90: 35 | J90: 49.16999999999996
A91: ORD100089 | B91: 44930.708 | C91: Delhi | D91: Tandoori Nights | E91: 862.38 | F91: 31.54 | G91: 450.67 | H91: Cash | I91: 58 | J91: 443.24999999999994
A92: ORD100090 | B92: 44930.75 | C92: Bangalore | D92: South Express | E92: 140.68 | F92: 4.56 | G92: 398.58 | H92: Card | I92: 36 | J92: -253.34
A93: ORD100091 | B93: 44930.792 | C93: Bangalore | D93: Biryani House | E93: 271.78 | F93: 27.19 | G93: 81.04 | H93: Cash | I93: 54 | J93: 217.92999999999995
A94: ORD100092 | B94: 44930.833 | C94: Mumbai | D94: South Express | E94: 440.94 | F94: 96.74 | G94: 218.75 | H94: UPI | I94: 44 | J94: 318.92999999999995
A95: ORD100093 | B95: 44930.875 | C95: Hyderabad | D95: Spice Hub | E95: 602.4 | F95: 88.02 | G95: 12.61 | H95: Wallet | I95: 34 | J95: 677.81
A96: ORD100094 | B96: 44930.917 | C96: Chennai | D96: Tandoori Nights | E96: 1695.39 | F96: 21.46 | G96: 214.1 | H96: Cash | I96: 59 | J96: 1502.7500000000002
A97: ORD100095 | B97: 44930.958 | C97: Bangalore | D97: Tandoori Nights | E97: 1216.42 | F97: 43.9 | G97: 383.08 | H97: Cash | I97: 14 | J97: 877.2400000000002
A98: ORD100096 | B98: 44931 | C98: Pune | D98: Urban Tadka | E98: 576.28 | F98: 74.55 | G98: 268.8 | H98: Card | I98: 51 | J98: 382.0299999999999
A99: ORD100097 | B99: 44931.042 | C99: Pune | D99: South Express | E99: 1496.37 | F99: 35.54 | G99: 243.35 | H99: Cash | I99: 82 | J99: 1288.56
A100: ORD100098 | B100: 44931.083 | C100: Delhi | D100: Biryani House | E100: 1022.35 | F100: 77.06 | G100: 487.2 | H100: UPI | I100: 16 | J100: 612.21
...

Sheet Cleaned Data
A1: Order_ID | B1: Order_Time | C1: City | D1: Restaurant | E1: Order_Value | F1: Delivery_Fee | G1: Discount | H1: Payment_Mode | I1: Delivery_Time_Min | J1: Final_Amount_Old | K1: Final_Amount | L1: Year | M1: Month | N1: Hour | O1: Order_Size
A2: ORD100000 | B2: 44927 | C2: Kolkata | D2: Pizza Corner | E2: 1349.85 | F2: 21.28 | G2: 462.51 | H2: Card | I2: 45 | J2: 908.6199999999999 | K2: =Table1[[#This Row],[Order_Value]]+Table1[[#This Row],[Delivery_Fee]]-Table1[[#This Row],[Discount]] -> 908.62 | L2: =YEAR(Table1[[#This Row],[Order_Time]]) -> 2023 | M2: =TEXT(Table1[[#This Row],[Order_Time]],"MMM") -> Jan | N2: =HOUR(Table1[[#This Row],[Order_Time]]) -> 0 | O2: =IF(Table1[[#This Row],[Order_Value]]>1000,"High","Low") -> High
A3: ORD100001 | B3: 44927.042 | C3: Hyderabad | D3: South Express | E3: 528.88 | F3: 64.92 | G3: 233.45 | H3: Card | I3: 82 | J3: 360.34999999999997 | K3: =Table1[[#This Row],[Order_Value]]+Table1[[#This Row],[Delivery_Fee]]-Table1[[#This Row],[Discount]] -> 360.35 | L3: =YEAR(Table1[[#This Row],[Order_Time]]) -> 2023 | M3: =TEXT(Table1[[#This Row],[Order_Time]],"MMM") -> Jan | N3: =HOUR(Table1[[#This Row],[Order_Time]]) -> 1 | O3: =IF(Table1[[#This Row],[Order_Value]]>1000,"High","Low") -> Low
A4: ORD100002 | B4: 44927.083 | C4: Chennai | D4: Pizza Corner | E4: 1590.35 | F4: 93.1 | G4: 326.73 | H4: Wallet | I4: 15 | J4: 1356.7199999999998 | K4: =Table1[[#This Row],[Order_Value]]+Table1[[#This Row],[Delivery_Fee]]-Table1[[#This Row],[Discount]] -> 1356.72 | L4: =YEAR(Table1[[#This Row],[Order_Time]]) -> 2023 | M4: =TEXT(Table1[[#This Row],[Order_Time]],"MMM") -> Jan | N4: =HOUR(Table1[[#This Row],[Order_Time]]) -> 2 | O4: =IF(Table1[[#This Row],[Order_Value]]>1000,"High","Low") -> High
A5: ORD100003 | B5: 44927.125 | C5: Delhi | D5: South Express | E5: 1834.73 | F5: 72.82 | G5: 92.2 | H5: Card | I5: 57 | J5: 1815.35 | K5: =Table1[[#This Row],[Order_Value]]+Table1[[#This Row],[Delivery_Fee]]-Table1[[#This Row],[Discount]] -> 1815.35 | L5: =YEAR(Table1[[#This Row],[Order_Time]]) -> 2023 | M5: =TEXT(Table1[[#This Row],[Order_Time]],"MMM") -> Jan | N5: =HOUR(Table1[[#This Row],[Order_Time]]) -> 3 | O5: =IF(Table1[[#This Row],[Order_Value]]>1000,"High","Low") -> High
A6: ORD100004 | B6: 44927.167 | C6: Mumbai | D6: Urban Tadka | E6: 1374.42 | F6: 50.05 | G6: 394.49 | H6: Cash | I6: 55 | J6: 1029.98 | K6: =Table1[[#This Row],[Order_Value]]+Table1[[#This Row],[Delivery_Fee]]-Table1[[#This Row],[Discount]] -> 1029.98 | L6: =YEAR(Table1[[#This Row],[Order_Time]]) -> 2023 | M6: =TEXT(Table1[[#This Row],[Order_Time]],"MMM") -> Jan | N6: =HOUR(Table1[[#This Row],[Order_Time]]) -> 4 | O6: =IF(Table1[[#This Row],[Order_Value]]>1000,"High","Low") -> High
A7: ORD100005 | B7: 44927.208 | C7: Hyderabad | D7: Tandoori Nights | E7: 1935.57 | F7: 5.7 | G7: 365.14 | H7: Wallet | I7: 28 | J7: 1576.13 | K7: =Table1[[#This Row],[Order_Value]]+Table1[[#This Row],[Delivery_Fee]]-Table1[[#This Row],[Discount]] -> 1576.13 | L7: =YEAR(Table1[[#This Row],[Order_Time]]) -> 2023 | M7: =TEXT(Table1[[#This Row],[Order_Time]],"MMM") -> Jan | N7: =HOUR(Table1[[#This Row],[Order_Time]]) -> 5 | O7: =IF(Table1[[#This Row],[Order_Value]]>1000,"High","Low") -> High
A8: ORD100006 | B8: 44927.25 | C8: Kolkata | D8: Tandoori Nights | E8: 944.53 | F8: 0.76 | G8: 372.22 | H8: UPI | I8: 85 | J8: 573.0699999999999 | K8: =Table1[[#This Row],[Order_Value]]+Table1[[#This Row],[Delivery_Fee]]-Table1[[#This Row],[Discount]] -> 573.07 | L8: =YEAR(Table1[[#This Row],[Order_Time]]) -> 2023 | M8: =TEXT(Table1[[#This Row],[Order_Time]],"MMM") -> Jan | N8: =HOUR(Table1[[#This Row],[Order_Time]]) -> 6 | O8: =IF(Table1[[#This Row],[Order_Value]]>1000,"High","Low") -> Low
A9: ORD100007 | B9: 44927.292 | C9: Delhi | D9: Spice Hub | E9: 1208.05 | F9: 97.27 | G9: 137.99 | H9: UPI | I9: 48 | J9: 1167.33 | K9: =Table1[[#This Row],[Order_Value]]+Table1[[#This Row],[Delivery_Fee]]-Table1[[#This Row],[Discount]] -> 1167.33 | L9: =YEAR(Table1[[#This Row],[Order_Time]]) -> 2023 | M9: =TEXT(Table1[[#This Row],[Order_Time]],"MMM") -> Jan | N9: =HOUR(Table1[[#This Row],[Order_Time]]) -> 7 | O9: =IF(Table1[[#This Row],[Order_Value]]>1000,"High","Low") -> High
A10: ORD100008 | B10: 44927.333 | C10: Delhi | D10: Urban Tadka | E10: 572.48 | F10: 23.16 | G10: 177.53 | H10: UPI | I10: 76 | J10: 418.11 | K10: =Table1[[#This Row],[Order_Value]]+Table1[[#This Row],[Delivery_Fee]]-Table1[[#This Row],[Discount]] -> 418.11 | L10: =YEAR(Table1[[#This Row],[Order_Time]]) -> 2023 | M10: =TEXT(Table1[[#This Row],[Order_Time]],"MMM") -> Jan | N10: =HOUR(Table1[[#This Row],[Order_Time]]) -> 8 | O10: =IF(Table1[[#This Row],[Order_Value]]>1000,"High","Low") -> Low
A11: ORD100009 | B11: 44927.375 | C11: Mumbai | D11: Pizza Corner | E11: 551.64 | F11: 54.33 | G11: 308.42 | H11: UPI | I11: 13 | J11: 297.55 | K11: =Table1[[#This Row],[Order_Value]]+Table1[[#This Row],[Delivery_Fee]]-Table1[[#This Row],[Discount]] -> 297.55 | L11: =YEAR(Table1[[#This Row],[Order_Time]]) -> 2023 | M11: =TEXT(Table1[[#This Row],[Order_Time]],"MMM") -> Jan | N11: =HOUR(Table1[[#This Row],[Order_Time]]) -> 9 | O11: =IF(Table1[[#This Row],[Order_Value]]>1000,"High","Low") -> Low
A12: ORD100010 | B12: 44927.417 | C12: Chennai | D12: South Express | E12: 483.8 | F12: 64.17 | G12: 352.64 | H12: Card | I12: 72 | J12: 195.33000000000004 | K12: =Table1[[#This Row],[Order_Value]]+Table1[[#This Row],[Delivery_Fee]]-Table1[[#This Row],[Discount]] -> 195.33 | L12: =YEAR(Table1[[#This Row],[Order_Time]]) -> 2023 | M12: =TEXT(Table1[[#This Row],[Order_Time]],"MMM") -> Jan | N12: =HOUR(Table1[[#This Row],[Order_Time]]) -> 10 | O12: =IF(Table1[[#This Row],[Order_Value]]>1000,"High","Low") -> Low
A13: ORD100011 | B13: 44927.458 | C13: Kolkata | D13: Biryani House | E13: 1838.77 | F13: 21.35 | G13: 198.95 | H13: Cash | I13: 10 | J13: 1661.1699999999998 | K13: =Table1[[#This Row],[Order_Value]]+Table1[[#This Row],[Delivery_Fee]]-Table1[[#This Row],[Discount]] -> 1661.17 | L13: =YEAR(Table1[[#This Row],[Order_Time]]) -> 2023 | M13: =TEXT(Table1[[#This Row],[Order_Time]],"MMM") -> Jan | N13: =HOUR(Table1[[#This Row],[Order_Time]]) -> 11 | O13: =IF(Table1[[#This Row],[Order_Value]]>1000,"High","Low") -> High
A14: ORD100012 | B14: 44927.5 | C14: Chennai | D14: Pizza Corner | E14: 886.72 | F14: 12.85 | G14: 26.19 | H14: Cash | I14: 82 | J14: 873.38 | K14: =Table1[[#This Row],[Order_Value]]+Table1[[#This Row],[Delivery_Fee]]-Table1[[#This Row],[Discount]] -> 873.38 | L14: =YEAR(Table1[[#This Row],[Order_Time]]) -> 2023 | M14: =TEXT(Table1[[#This Row],[Order_Time]],"MMM") -> Jan | N14: =HOUR(Table1[[#This Row],[Order_Time]]) -> 12 | O14: =IF(Table1[[#This Row],[Order_Value]]>1000,"High","Low") -> Low
A15: ORD100013 | B15: 44927.542 | C15: Pune | D15: Urban Tadka | E15: 1043.69 | F15: 79.71 | G15: 356.89 | H15: Card | I15: 58 | J15: 766.5100000000001 | K15: =Table1[[#This Row],[Order_Value]]+Table1[[#This Row],[Delivery_Fee]]-Table1[[#This Row],[Discount]] -> 766.51 | L15: =YEAR(Table1[[#This Row],[Order_Time]]) -> 2023 | M15: =TEXT(Table1[[#This Row],[Order_Time]],"MMM") -> Jan | N15: =HOUR(Table1[[#This Row],[Order_Time]]) -> 13 | O15: =IF(Table1[[#This Row],[Order_Value]]>1000,"High","Low") -> High
A16: ORD100014 | B16: 44927.583 | C16: Mumbai | D16: Tandoori Nights | E16: 1920.18 | F16: 11.99 | G16: 68.19 | H16: UPI | I16: 45 | J16: 1863.98 | K16: =Table1[[#This Row],[Order_Value]]+Table1[[#This Row],[Delivery_Fee]]-Table1[[#This Row],[Discount]] -> 1863.98 | L16: =YEAR(Table1[[#This Row],[Order_Time]]) -> 2023 | M16: =TEXT(Table1[[#This Row],[Order_Time]],"MMM") -> Jan | N16: =HOUR(Table1[[#This Row],[Order_Time]]) -> 14 | O16: =IF(Table1[[#This Row],[Order_Value]]>1000,"High","Low") -> High
A17: ORD100015 | B17: 44927.625 | C17: Unknown | D17: Biryani House | E17: 404.41 | F17: 32.97 | G17: 118.16 | H17: UPI | I17: 79 | J17: 319.22 | K17: =Table1[[#This Row],[Order_Value]]+Table1[[#This Row],[Delivery_Fee]]-Table1[[#This Row],[Discount]] -> 319.22 | L17: =YEAR(Table1[[#This Row],[Order_Time]]) -> 2023 | M17: =TEXT(Table1[[#This Row],[Order_Time]],"MMM") -> Jan | N17: =HOUR(Table1[[#This Row],[Order_Time]]) -> 15 | O17: =IF(Table1[[#This Row],[Order_Value]]>1000,"High","Low") -> Low
A18: ORD100016 | B18: 44927.667 | C18: Chennai | D18: Pizza Corner | E18: 895.09 | F18: 21.67 | G18: 412.06 | H18: Wallet | I18: 10 | J18: 504.7 | K18: =Table1[[#This Row],[Order_Value]]+Table1[[#This Row],[Delivery_Fee]]-Table1[[#This Row],[Discount]] -> 504.7 | L18: =YEAR(Table1[[#This Row],[Order_Time]]) -> 2023 | M18: =TEXT(Table1[[#This Row],[Order_Time]],"MMM") -> Jan | N18: =HOUR(Table1[[#This Row],[Order_Time]]) -> 16 | O18: =IF(Table1[[#This Row],[Order_Value]]>1000,"High","Low") -> Low
A19: ORD100017 | B19: 44927.708 | C19: Pune | D19: Tandoori Nights | E19: 1861.77 | F19: 12.5 | G19: 29.64 | H19: Cash | I19: 73 | J19: 1844.6299999999999 | K19: =Table1[[#This Row],[Order_Value]]+Table1[[#This Row],[Delivery_Fee]]-Table1[[#This Row],[Discount]] -> 1844.63 | L19: =YEAR(Table1[[#This Row],[Order_Time]]) -> 2023 | M19: =TEXT(Table1[[#This Row],[Order_Time]],"MMM") -> Jan | N19: =HOUR(Table1[[#This Row],[Order_Time]]) -> 17 | O19: =IF(Table1[[#This Row],[Order_Value]]>1000,"High","Low") -> High
A20: ORD100018 | B20: 44927.75 | C20: Kolkata | D20: Spice Hub | E20: 1183.04 | F20: 71.24 | G20: 239.14 | H20: UPI | I20: 52 | J20: 1015.14 | K20: =Table1[[#This Row],[Order_Value]]+Table1[[#This Row],[Delivery_Fee]]-Table1[[#This Row],[Discount]] -> 1015.14 | L20: =YEAR(Table1[[#This Row],[Order_Time]]) -> 2023 | M20: =TEXT(Table1[[#This Row],[Order_Time]],"MMM") -> Jan | N20: =HOUR(Table1[[#This Row],[Order_Time]]) -> 18 | O20: =IF(Table1[[#This Row],[Order_Value]]>1000,"High","Low") -> High
A21: ORD100019 | B21: 44927.792 | C21: Bangalore | D21: Urban Tadka | E21: 827.72 | F21: 73.55 | G21: 59.43 | H21: Cash | I21: 38 | J21: 841.84 | K21: =Table1[[#This Row],[Order_Value]]+Table1[[#This Row],[Delivery_Fee]]-Table1[[#This Row],[Discount]] -> 841.84 | L21: =YEAR(Table1[[#This Row],[Order_Time]]) -> 2023 | M21: =TEXT(Table1[[#This Row],[Order_Time]],"MMM") -> Jan | N21: =HOUR(Table1[[#This Row],[Order_Time]]) -> 19 | O21: =IF(Table1[[#This Row],[Order_Value]]>1000,"High","Low") -> Low
A22: ORD100020 | B22: 44927.833 | C22: Chennai | D22: Tandoori Nights | E22: 1091.84 | F22: 82.62 | G22: 188.33 | H22: UPI | I22: 27 | J22: 986.13 | K22: =Table1[[#This Row],[Order_Value]]+Table1[[#This Row],[Delivery_Fee]]-Table1[[#This Row],[Discount]] -> 986.13 | L22: =YEAR(Table1[[#This Row],[Order_Time]]) -> 2023 | M22: =TEXT(Table1[[#This Row],[Order_Time]],"MMM") -> Jan | N22: =HOUR(Table1[[#This Row],[Order_Time]]) -> 20 | O22: =IF(Table1[[#This Row],[Order_Value]]>1000,"High","Low") -> High
A23: ORD100021 | B23: 44927.875 | C23: Hyderabad | D23: South Express | E23: 1972.65 | F23: 73.61 | G23: 335.02 | H23: UPI | I23: 40 | J23: 1711.24 | K23: =Table1[[#This Row],[Order_Value]]+Table1[[#This Row],[Delivery_Fee]]-Table1[[#This Row],[Discount]] -> 1711.24 | L23: =YEAR(Table1[[#This Row],[Order_Time]]) -> 2023 | M23: =TEXT(Table1[[#This Row],[Order_Time]],"MMM") -> Jan | N23: =HOUR(Table1[[#This Row],[Order_Time]]) -> 21 | O23: =IF(Table1[[#This Row],[Order_Value]]>1000,"High","Low") -> High
A24: ORD100022 | B24: 44927.917 | C24: Chennai | D24: South Express | E24: 650.05 | F24: 85.15 | G24: 307.57 | H24: Wallet | I24: 37 | J24: 427.62999999999994 | K24: =Table1[[#This Row],[Order_Value]]+Table1[[#This Row],[Delivery_Fee]]-Table1[[#This Row],[Discount]] -> 427.63 | L24: =YEAR(Table1[[#This Row],[Order_Time]]) -> 2023 | M24: =TEXT(Table1[[#This Row],[Order_Time]],"MMM") -> Jan | N24: =HOUR(Table1[[#This Row],[Order_Time]]) -> 22 | O24: =IF(Table1[[#This Row],[Order_Value]]>1000,"High","Low") -> Low
A25: ORD100023 | B25: 44927.958 | C25: Bangalore | D25: Urban Tadka | E25: 656.55 | F25: 41.64 | G25: 420.57 | H25: Card | I25: 81 | J25: 277.61999999999995 | K25: =Table1[[#This Row],[Order_Value]]+Table1[[#This Row],[Delivery_Fee]]-Table1[[#This Row],[Discount]] -> 277.62 | L25: =YEAR(Table1[[#This Row],[Order_Time]]) -> 2023 | M25: =TEXT(Table1[[#This Row],[Order_Time]],"MMM") -> Jan | N25: =HOUR(Table1[[#This Row],[Order_Time]]) -> 23 | O25: =IF(Table1[[#This Row],[Order_Value]]>1000,"High","Low") -> Low
A26: ORD100024 | B26: 44928 | C26: Chennai | D26: Pizza Corner | E26: 1239.17 | F26: 90.46 | G26: 90.59 | H26: Card | I26: 12 | J26: 1239.0400000000002 | K26: =Table1[[#This Row],[Order_Value]]+Table1[[#This Row],[Delivery_Fee]]-Table1[[#This Row],[Discount]] -> 1239.04 | L26: =YEAR(Table1[[#This Row],[Order_Time]]) -> 2023 | M26: =TEXT(Table1[[#This Row],[Order_Time]],"MMM") -> Jan | N26: =HOUR(Table1[[#This Row],[Order_Time]]) -> 0 | O26: =IF(Table1[[#This Row],[Order_Value]]>1000,"High","Low") -> High
A27: ORD100025 | B27: 44928.042 | C27: Kolkata | D27: South Express | E27: 1898.75 | F27: 10.28 | G27: 371.4 | H27: UPI | I27: 26 | J27: 1537.63 | K27: =Table1[[#This Row],[Order_Value]]+Table1[[#This Row],[Delivery_Fee]]-Table1[[#This Row],[Discount]] -> 1537.63 | L27: =YEAR(Table1[[#This Row],[Order_Time]]) -> 2023 | M27: =TEXT(Table1[[#This Row],[Order_Time]],"MMM") -> Jan | N27: =HOUR(Table1[[#This Row],[Order_Time]]) -> 1 | O27: =IF(Table1[[#This Row],[Order_Value]]>1000,"High","Low") -> High
A28: ORD100026 | B28: 44928.083 | C28: Pune | D28: Pizza Corner | E28: 1879.83 | F28: 34.22 | G28: 441.52 | H28: Cash | I28: 54 | J28: 1472.53 | K28: =Table1[[#This Row],[Order_Value]]+Table1[[#This Row],[Delivery_Fee]]-Table1[[#This Row],[Discount]] -> 1472.53 | L28: =YEAR(Table1[[#This Row],[Order_Time]]) -> 2023 | M28: =TEXT(Table1[[#This Row],[Order_Time]],"MMM") -> Jan | N28: =HOUR(Table1[[#This Row],[Order_Time]]) -> 2 | O28: =IF(Table1[[#This Row],[Order_Value]]>1000,"High","Low") -> High
A29: ORD100027 | B29: 44928.125 | C29: Bangalore | D29: South Express | E29: 1358.03 | F29: 24.87 | G29: 300.22 | H29: Card | I29: 19 | J29: 1082.6799999999998 | K29: =Table1[[#This Row],[Order_Value]]+Table1[[#This Row],[Delivery_Fee]]-Table1[[#This Row],[Discount]] -> 1082.68 | L29: =YEAR(Table1[[#This Row],[Order_Time]]) -> 2023 | M29: =TEXT(Table1[[#This Row],[Order_Time]],"MMM") -> Jan | N29: =HOUR(Table1[[#This Row],[Order_Time]]) -> 3 | O29: =IF(Table1[[#This Row],[Order_Value]]>1000,"High","Low") -> High
A30: ORD100028 | B30: 44928.167 | C30: Chennai | D30: Urban Tadka | E30: 931.37 | F30: 1.31 | G30: 368.09 | H30: Cash | I30: 55 | J30: 564.5899999999999 | K30: =Table1[[#This Row],[Order_Value]]+Table1[[#This Row],[Delivery_Fee]]-Table1[[#This Row],[Discount]] -> 564.59 | L30: =YEAR(Table1[[#This Row],[Order_Time]]) -> 2023 | M30: =TEXT(Table1[[#This Row],[Order_Time]],"MMM") -> Jan | N30: =HOUR(Table1[[#This Row],[Order_Time]]) -> 4 | O30: =IF(Table1[[#This Row],[Order_Value]]>1000,"High","Low") -> Low
A31: ORD100029 | B31: 44928.208 | C31: Mumbai | D31: Pizza Corner | E31: 796.86 | F31: 38.64 | G31: 464.24 | H31: Wallet | I31: 15 | J31: 371.26 | K31: =Table1[[#This Row],[Order_Value]]+Table1[[#This Row],[Delivery_Fee]]-Table1[[#This Row],[Discount]] -> 371.26 | L31: =YEAR(Table1[[#This Row],[Order_Time]]) -> 2023 | M31: =TEXT(Table1[[#This Row],[Order_Time]],"MMM") -> Jan | N31: =HOUR(Table1[[#This Row],[Order_Time]]) -> 5 | O31: =IF(Table1[[#This Row],[Order_Value]]>1000,"High","Low") -> Low
A32: ORD100030 | B32: 44928.25 | C32: Mumbai | D32: Urban Tadka | E32: 1861.19 | F32: 54.93 | G32: 153.03 | H32: Cash | I32: 37 | J32: 1763.0900000000001 | K32: =Table1[[#This Row],[Order_Value]]+Table1[[#This Row],[Delivery_Fee]]-Table1[[#This Row],[Discount]] -> 1763.09 | L32: =YEAR(Table1[[#This Row],[Order_Time]]) -> 2023 | M32: =TEXT(Table1[[#This Row],[Order_Time]],"MMM") -> Jan | N32: =HOUR(Table1[[#This Row],[Order_Time]]) -> 6 | O32: =IF(Table1[[#This Row],[Order_Value]]>1000,"High","Low") -> High
A33: ORD100031 | B33: 44928.292 | C33: Pune | D33: Biryani House | E33: 916.22 | F33: 61.65 | G33: 246.7 | H33: Card | I33: 48 | J33: 731.1700000000001 | K33: =Table1[[#This Row],[Order_Value]]+Table1[[#This Row],[Delivery_Fee]]-Table1[[#This Row],[Discount]] -> 731.17 | L33: =YEAR(Table1[[#This Row],[Order_Time]]) -> 2023 | M33: =TEXT(Table1[[#This Row],[Order_Time]],"MMM") -> Jan | N33: =HOUR(Table1[[#This Row],[Order_Time]]) -> 7 | O33: =IF(Table1[[#This Row],[Order_Value]]>1000,"High","Low") -> Low
A34: ORD100032 | B34: 44928.333 | C34: Delhi | D34: Spice Hub | E34: 1747.22 | F34: 32.86 | G34: 363.05 | H34: Cash | I34: 81 | J34: 1417.03 | K34: =Table1[[#This Row],[Order_Value]]+Table1[[#This Row],[Delivery_Fee]]-Table1[[#This Row],[Discount]] -> 1417.03 | L34: =YEAR(Table1[[#This Row],[Order_Time]]) -> 2023 | M34: =TEXT(Table1[[#This Row],[Order_Time]],"MMM") -> Jan | N34: =HOUR(Table1[[#This Row],[Order_Time]]) -> 8 | O34: =IF(Table1[[#This Row],[Order_Value]]>1000,"High","Low") -> High
A35: ORD100033 | B35: 44928.375 | C35: Pune | D35: South Express | E35: 1741.44 | F35: 84.4 | G35: 17.32 | H35: Cash | I35: 87 | J35: 1808.5200000000002 | K35: =Table1[[#This Row],[Order_Value]]+Table1[[#This Row],[Delivery_Fee]]-Table1[[#This Row],[Discount]] -> 1808.52 | L35: =YEAR(Table1[[#This Row],[Order_Time]]) -> 2023 | M35: =TEXT(Table1[[#This Row],[Order_Time]],"MMM") -> Jan | N35: =HOUR(Table1[[#This Row],[Order_Time]]) -> 9 | O35: =IF(Table1[[#This Row],[Order_Value]]>1000,"High","Low") -> High
A36: ORD100034 | B36: 44928.417 | C36: Kolkata | D36: Urban Tadka | E36: 691.22 | F36: 75.47 | G36: 239.04 | H36: Cash | I36: 15 | J36: 527.6500000000001 | K36: =Table1[[#This Row],[Order_Value]]+Table1[[#This Row],[Delivery_Fee]]-Table1[[#This Row],[Discount]] -> 527.65 | L36: =YEAR(Table1[[#This Row],[Order_Time]]) -> 2023 | M36: =TEXT(Table1[[#This Row],[Order_Time]],"MMM") -> Jan | N36: =HOUR(Table1[[#This Row],[Order_Time]]) -> 10 | O36: =IF(Table1[[#This Row],[Order_Value]]>1000,"High","Low") -> Low
A37: ORD100035 | B37: 44928.458 | C37: Mumbai | D37: Urban Tadka | E37: 1796.48 | F37: 69.19 | G37: 407.96 | H37: Wallet | I37: 25 | J37: 1457.71 | K37: =Table1[[#This Row],[Order_Value]]+Table1[[#This Row],[Delivery_Fee]]-Table1[[#This Row],[Discount]] -> 1457.71 | L37: =YEAR(Table1[[#This Row],[Order_Time]]) -> 2023 | M37: =TEXT(Table1[[#This Row],[Order_Time]],"MMM") -> Jan | N37: =HOUR(Table1[[#This Row],[Order_Time]]) -> 11 | O37: =IF(Table1[[#This Row],[Order_Value]]>1000,"High","Low") -> High
A38: ORD100036 | B38: 44928.5 | C38: Mumbai | D38: Tandoori Nights | E38: 1527.5 | F38: 57.69 | G38: 164.33 | H38: Wallet | I38: 37 | J38: 1420.8600000000001 | K38: =Table1[[#This Row],[Order_Value]]+Table1[[#This Row],[Delivery_Fee]]-Table1[[#This Row],[Discount]] -> 1420.86 | L38: =YEAR(Table1[[#This Row],[Order_Time]]) -> 2023 | M38: =TEXT(Table1[[#This Row],[Order_Time]],"MMM") -> Jan | N38: =HOUR(Table1[[#This Row],[Order_Time]]) -> 12 | O38: =IF(Table1[[#This Row],[Order_Value]]>1000,"High","Low") -> High
A39: ORD100037 | B39: 44928.542 | C39: Kolkata | D39: Urban Tadka | E39: 915.17 | F39: 4.02 | G39: 112.28 | H39: Card | I39: 58 | J39: 806.91 | K39: =Table1[[#This Row],[Order_Value]]+Table1[[#This Row],[Delivery_Fee]]-Table1[[#This Row],[Discount]] -> 806.91 | L39: =YEAR(Table1[[#This Row],[Order_Time]]) -> 2023 | M39: =TEXT(Table1[[#This Row],[Order_Time]],"MMM") -> Jan | N39: =HOUR(Table1[[#This Row],[Order_Time]]) -> 13 | O39: =IF(Table1[[#This Row],[Order_Value]]>1000,"High","Low") -> Low
A40: ORD100038 | B40: 44928.583 | C40: Pune | D40: Biryani House | E40: 1123.85 | F40: 0.21 | G40: 192.29 | H40: UPI | I40: 38 | J40: 931.77 | K40: =Table1[[#This Row],[Order_Value]]+Table1[[#This Row],[Delivery_Fee]]-Table1[[#This Row],[Discount]] -> 931.77 | L40: =YEAR(Table1[[#This Row],[Order_Time]]) -> 2023 | M40: =TEXT(Table1[[#This Row],[Order_Time]],"MMM") -> Jan | N40: =HOUR(Table1[[#This Row],[Order_Time]]) -> 14 | O40: =IF(Table1[[#This Row],[Order_Value]]>1000,"High","Low") -> High
A41: ORD100039 | B41: 44928.625 | C41: Mumbai | D41: Spice Hub | E41: 1744.57 | F41: 8.27 | G41: 351.98 | H41: UPI | I41: 54 | J41: 1400.86 | K41: =Table1[[#This Row],[Order_Value]]+Table1[[#This Row],[Delivery_Fee]]-Table1[[#This Row],[Discount]] -> 1400.86 | L41: =YEAR(Table1[[#This Row],[Order_Time]]) -> 2023 | M41: =TEXT(Table1[[#This Row],[Order_Time]],"MMM") -> Jan | N41: =HOUR(Table1[[#This Row],[Order_Time]]) -> 15 | O41: =IF(Table1[[#This Row],[Order_Value]]>1000,"High","Low") -> High
A42: ORD100040 | B42: 44928.667 | C42: Mumbai | D42: Biryani House | E42: 1181.02 | F42: 48.62 | G42: 409.19 | H42: Card | I42: 56 | J42: 820.4499999999998 | K42: =Table1[[#This Row],[Order_Value]]+Table1[[#This Row],[Delivery_Fee]]-Table1[[#This Row],[Discount]] -> 820.45 | L42: =YEAR(Table1[[#This Row],[Order_Time]]) -> 2023 | M42: =TEXT(Table1[[#This Row],[Order_Time]],"MMM") -> Jan | N42: =HOUR(Table1[[#This Row],[Order_Time]]) -> 16 | O42: =IF(Table1[[#This Row],[Order_Value]]>1000,"High","Low") -> High
A43: ORD100041 | B43: 44928.708 | C43: Delhi | D43: Biryani House | E43: 1335.92 | F43: 17.61 | G43: 178.68 | H43: UPI | I43: 77 | J43: 1174.85 | K43: =Table1[[#This Row],[Order_Value]]+Table1[[#This Row],[Delivery_Fee]]-Table1[[#This Row],[Discount]] -> 1174.85 | L43: =YEAR(Table1[[#This Row],[Order_Time]]) -> 2023 | M43: =TEXT(Table1[[#This Row],[Order_Time]],"MMM") -> Jan | N43: =HOUR(Table1[[#This Row],[Order_Time]]) -> 17 | O43: =IF(Table1[[#This Row],[Order_Value]]>1000,"High","Low") -> High
A44: ORD100042 | B44: 44928.75 | C44: Chennai | D44: Biryani House | E44: 932.56 | F44: 57.38 | G44: 376.9 | H44: UPI | I44: 69 | J44: 613.04 | K44: =Table1[[#This Row],[Order_Value]]+Table1[[#This Row],[Delivery_Fee]]-Table1[[#This Row],[Discount]] -> 613.04 | L44: =YEAR(Table1[[#This Row],[Order_Time]]) -> 2023 | M44: =TEXT(Table1[[#This Row],[Order_Time]],"MMM") -> Jan | N44: =HOUR(Table1[[#This Row],[Order_Time]]) -> 18 | O44: =IF(Table1[[#This Row],[Order_Value]]>1000,"High","Low") -> Low
A45: ORD100043 | B45: 44928.792 | C45: Mumbai | D45: Pizza Corner | E45: 0 | F45: 21.79 | G45: 463.58 | H45: Wallet | I45: 36 | K45: =Table1[[#This Row],[Order_Value]]+Table1[[#This Row],[Delivery_Fee]]-Table1[[#This Row],[Discount]] -> -441.79 | L45: =YEAR(Table1[[#This Row],[Order_Time]]) -> 2023 | M45: =TEXT(Table1[[#This Row],[Order_Time]],"MMM") -> Jan | N45: =HOUR(Table1[[#This Row],[Order_Time]]) -> 19 | O45: =IF(Table1[[#This Row],[Order_Value]]>1000,"High","Low") -> Low
A46: ORD100044 | B46: 44928.833 | C46: Delhi | D46: Spice Hub | E46: 1198.01 | F46: 72.52 | G46: 153.15 | H46: Cash | I46: 10 | J46: 1117.3799999999999 | K46: =Table1[[#This Row],[Order_Value]]+Table1[[#This Row],[Delivery_Fee]]-Table1[[#This Row],[Discount]] -> 1117.38 | L46: =YEAR(Table1[[#This Row],[Order_Time]]) -> 2023 | M46: =TEXT(Table1[[#This Row],[Order_Time]],"MMM") -> Jan | N46: =HOUR(Table1[[#This Row],[Order_Time]]) -> 20 | O46: =IF(Table1[[#This Row],[Order_Value]]>1000,"High","Low") -> High
A47: ORD100045 | B47: 44928.875 | C47: Delhi | D47: Tandoori Nights | E47: 979.37 | F47: 71.91 | G47: 138.2 | H47: Cash | I47: 54 | J47: 913.0799999999999 | K47: =Table1[[#This Row],[Order_Value]]+Table1[[#This Row],[Delivery_Fee]]-Table1[[#This Row],[Discount]] -> 913.08 | L47: =YEAR(Table1[[#This Row],[Order_Time]]) -> 2023 | M47: =TEXT(Table1[[#This Row],[Order_Time]],"MMM") -> Jan | N47: =HOUR(Table1[[#This Row],[Order_Time]]) -> 21 | O47: =IF(Table1[[#This Row],[Order_Value]]>1000,"High","Low") -> Low
A48: ORD100046 | B48: 44928.917 | C48: Kolkata | D48: Urban Tadka | E48: 586.39 | F48: 21.76 | G48: 87.74 | H48: UPI | I48: 48 | J48: 520.41 | K48: =Table1[[#This Row],[Order_Value]]+Table1[[#This Row],[Delivery_Fee]]-Table1[[#This Row],[Discount]] -> 520.41 | L48: =YEAR(Table1[[#This Row],[Order_Time]]) -> 2023 | M48: =TEXT(Table1[[#This Row],[Order_Time]],"MMM") -> Jan | N48: =HOUR(Table1[[#This Row],[Order_Time]]) -> 22 | O48: =IF(Table1[[#This Row],[Order_Value]]>1000,"High","Low") -> Low
A49: ORD100047 | B49: 44928.958 | C49: Hyderabad | D49: Tandoori Nights | E49: 1994.19 | F49: 82.9 | G49: 270.77 | H49: UPI | I49: 69 | J49: 1806.3200000000002 | K49: =Table1[[#This Row],[Order_Value]]+Table1[[#This Row],[Delivery_Fee]]-Table1[[#This Row],[Discount]] -> 1806.32 | L49: =YEAR(Table1[[#This Row],[Order_Time]]) -> 2023 | M49: =TEXT(Table1[[#This Row],[Order_Time]],"MMM") -> Jan | N49: =HOUR(Table1[[#This Row],[Order_Time]]) -> 23 | O49: =IF(Table1[[#This Row],[Order_Value]]>1000,"High","Low") -> High
A50: ORD100048 | B50: 44929 | C50: Bangalore | D50: South Express | E50: 291.86 | F50: 79.68 | G50: 388.68 | H50: UPI | I50: 54 | J50: -17.14 | K50: =Table1[[#This Row],[Order_Value]]+Table1[[#This Row],[Delivery_Fee]]-Table1[[#This Row],[Discount]] -> -17.14 | L50: =YEAR(Table1[[#This Row],[Order_Time]]) -> 2023 | M50: =TEXT(Table1[[#This Row],[Order_Time]],"MMM") -> Jan | N50: =HOUR(Table1[[#This Row],[Order_Time]]) -> 0 | O50: =IF(Table1[[#This Row],[Order_Value]]>1000,"High","Low") -> Low
A51: ORD100049 | B51: 44929.042 | C51: Mumbai | D51: South Express | E51: 806.98 | F51: 78.3 | G51: 304.13 | H51: UPI | I51: 50 | J51: 581.15 | K51: =Table1[[#This Row],[Order_Value]]+Table1[[#This Row],[Delivery_Fee]]-Table1[[#This Row],[Discount]] -> 581.15 | L51: =YEAR(Table1[[#This Row],[Order_Time]]) -> 2023 | M51: =TEXT(Table1[[#This Row],[Order_Time]],"MMM") -> Jan | N51: =HOUR(Table1[[#This Row],[Order_Time]]) -> 1 | O51: =IF(Table1[[#This Row],[Order_Value]]>1000,"High","Low") -> Low
A52: ORD100050 | B52: 44929.083 | C52: Delhi | D52: Spice Hub | E52: 1838.39 | F52: 53.36 | G52: 235.82 | H52: Card | I52: 25 | J52: 1655.93 | K52: =Table1[[#This Row],[Order_Value]]+Table1[[#This Row],[Delivery_Fee]]-Table1[[#This Row],[Discount]] -> 1655.93 | L52: =YEAR(Table1[[#This Row],[Order_Time]]) -> 2023 | M52: =TEXT(Table1[[#This Row],[Order_Time]],"MMM") -> Jan | N52: =HOUR(Table1[[#This Row],[Order_Time]]) -> 2 | O52: =IF(Table1[[#This Row],[Order_Value]]>1000,"High","Low") -> High
A53: ORD100051 | B53: 44929.125 | C53: Pune | D53: Urban Tadka | E53: 1956.27 | F53: 39.12 | G53: 376.7 | H53: Cash | I53: 69 | J53: 1618.6899999999998 | K53: =Table1[[#This Row],[Order_Value]]+Table1[[#This Row],[Delivery_Fee]]-Table1[[#This Row],[Discount]] -> 1618.69 | L53: =YEAR(Table1[[#This Row],[Order_Time]]) -> 2023 | M53: =TEXT(Table1[[#This Row],[Order_Time]],"MMM") -> Jan | N53: =HOUR(Table1[[#This Row],[Order_Time]]) -> 3 | O53: =IF(Table1[[#This Row],[Order_Value]]>1000,"High","Low") -> High
A54: ORD100052 | B54: 44929.167 | C54: Hyderabad | D54: South Express | E54: 149.31 | F54: 79.89 | G54: 205.7 | H54: Wallet | I54: 12 | J54: 23.5 | K54: =Table1[[#This Row],[Order_Value]]+Table1[[#This Row],[Delivery_Fee]]-Table1[[#This Row],[Discount]] -> 23.5 | L54: =YEAR(Table1[[#This Row],[Order_Time]]) -> 2023 | M54: =TEXT(Table1[[#This Row],[Order_Time]],"MMM") -> Jan | N54: =HOUR(Table1[[#This Row],[Order_Time]]) -> 4 | O54: =IF(Table1[[#This Row],[Order_Value]]>1000,"High","Low") -> Low
A55: ORD100053 | B55: 44929.208 | C55: Pune | D55: Urban Tadka | E55: 1544.89 | F55: 99.88 | G55: 287.35 | H55: Card | I55: 24 | J55: 1357.42 | K55: =Table1[[#This Row],[Order_Value]]+Table1[[#This Row],[Delivery_Fee]]-Table1[[#This Row],[Discount]] -> 1357.42 | L55: =YEAR(Table1[[#This Row],[Order_Time]]) -> 2023 | M55: =TEXT(Table1[[#This Row],[Order_Time]],"MMM") -> Jan | N55: =HOUR(Table1[[#This Row],[Order_Time]]) -> 5 | O55: =IF(Table1[[#This Row],[Order_Value]]>1000,"High","Low") -> High
A56: ORD100054 | B56: 44929.25 | C56: Kolkata | D56: Pizza Corner | E56: 685.19 | F56: 93 | G56: 221.81 | H56: Wallet | I56: 65 | J56: 556.3800000000001 | K56: =Table1[[#This Row],[Order_Value]]+Table1[[#This Row],[Delivery_Fee]]-Table1[[#This Row],[Discount]] -> 556.38 | L56: =YEAR(Table1[[#This Row],[Order_Time]]) -> 2023 | M56: =TEXT(Table1[[#This Row],[Order_Time]],"MMM") -> Jan | N56: =HOUR(Table1[[#This Row],[Order_Time]]) -> 6 | O56: =IF(Table1[[#This Row],[Order_Value]]>1000,"High","Low") -> Low
A57: ORD100055 | B57: 44929.292 | C57: Mumbai | D57: Spice Hub | E57: 1389.68 | F57: 87.44 | G57: 154.46 | H57: Cash | I57: 20 | J57: 1322.66 | K57: =Table1[[#This Row],[Order_Value]]+Table1[[#This Row],[Delivery_Fee]]-Table1[[#This Row],[Discount]] -> 1322.66 | L57: =YEAR(Table1[[#This Row],[Order_Time]]) -> 2023 | M57: =TEXT(Table1[[#This Row],[Order_Time]],"MMM") -> Jan | N57: =HOUR(Table1[[#This Row],[Order_Time]]) -> 7 | O57: =IF(Table1[[#This Row],[Order_Value]]>1000,"High","Low") -> High
A58: ORD100056 | B58: 44929.333 | C58: Mumbai | D58: South Express | E58: 1159.16 | F58: 39.07 | G58: 373.45 | H58: UPI | I58: 88 | J58: 824.78 | K58: =Table1[[#This Row],[Order_Value]]+Table1[[#This Row],[Delivery_Fee]]-Table1[[#This Row],[Discount]] -> 824.78 | L58: =YEAR(Table1[[#This Row],[Order_Time]]) -> 2023 | M58: =TEXT(Table1[[#This Row],[Order_Time]],"MMM") -> Jan | N58: =HOUR(Table1[[#This Row],[Order_Time]]) -> 8 | O58: =IF(Table1[[#This Row],[Order_Value]]>1000,"High","Low") -> High
A59: ORD100057 | B59: 44929.375 | C59: Hyderabad | D59: Pizza Corner | E59: 307.32 | F59: 83.33 | G59: 84.38 | H59: Cash | I59: 33 | J59: 306.27 | K59: =Table1[[#This Row],[Order_Value]]+Table1[[#This Row],[Delivery_Fee]]-Table1[[#This Row],[Discount]] -> 306.27 | L59: =YEAR(Table1[[#This Row],[Order_Time]]) -> 2023 | M59: =TEXT(Table1[[#This Row],[Order_Time]],"MMM") -> Jan | N59: =HOUR(Table1[[#This Row],[Order_Time]]) -> 9 | O59: =IF(Table1[[#This Row],[Order_Value]]>1000,"High","Low") -> Low
A60: ORD100058 | B60: 44929.417 | C60: Chennai | D60: Tandoori Nights | E60: 173.49 | F60: 75.62 | G60: 375.8 | H60: Cash | I60: 61 | J60: -126.69 | K60: =Table1[[#This Row],[Order_Value]]+Table1[[#This Row],[Delivery_Fee]]-Table1[[#This Row],[Discount]] -> -126.69 | L60: =YEAR(Table1[[#This Row],[Order_Time]]) -> 2023 | M60: =TEXT(Table1[[#This Row],[Order_Time]],"MMM") -> Jan | N60: =HOUR(Table1[[#This Row],[Order_Time]]) -> 10 | O60: =IF(Table1[[#This Row],[Order_Value]]>1000,"High","Low") -> Low
A61: ORD100059 | B61: 44929.458 | C61: Delhi | D61: South Express | E61: 1749.67 | F61: 4.59 | G61: 90.04 | H61: Wallet | I61: 56 | J61: 1664.22 | K61: =Table1[[#This Row],[Order_Value]]+Table1[[#This Row],[Delivery_Fee]]-Table1[[#This Row],[Discount]] -> 1664.22 | L61: =YEAR(Table1[[#This Row],[Order_Time]]) -> 2023 | M61: =TEXT(Table1[[#This Row],[Order_Time]],"MMM") -> Jan | N61: =HOUR(Table1[[#This Row],[Order_Time]]) -> 11 | O61: =IF(Table1[[#This Row],[Order_Value]]>1000,"High","Low") -> High
A62: ORD100060 | B62: 44929.5 | C62: Mumbai | D62: Biryani House | E62: 1806.59 | F62: 96.45 | G62: 76.59 | H62: UPI | I62: 29 | J62: 1826.45 | K62: =Table1[[#This Row],[Order_Value]]+Table1[[#This Row],[Delivery_Fee]]-Table1[[#This Row],[Discount]] -> 1826.45 | L62: =YEAR(Table1[[#This Row],[Order_Time]]) -> 2023 | M62: =TEXT(Table1[[#This Row],[Order_Time]],"MMM") -> Jan | N62: =HOUR(Table1[[#This Row],[Order_Time]]) -> 12 | O62: =IF(Table1[[#This Row],[Order_Value]]>1000,"High","Low") -> High
A63: ORD100061 | B63: 44929.542 | C63: Hyderabad | D63: Tandoori Nights | E63: 1995.73 | F63: 45.72 | G63: 314.98 | H63: Card | I63: 44 | J63: 1726.47 | K63: =Table1[[#This Row],[Order_Value]]+Table1[[#This Row],[Delivery_Fee]]-Table1[[#This Row],[Discount]] -> 1726.47 | L63: =YEAR(Table1[[#This Row],[Order_Time]]) -> 2023 | M63: =TEXT(Table1[[#This Row],[Order_Time]],"MMM") -> Jan | N63: =HOUR(Table1[[#This Row],[Order_Time]]) -> 13 | O63: =IF(Table1[[#This Row],[Order_Value]]>1000,"High","Low") -> High
A64: ORD100062 | B64: 44929.583 | C64: Chennai | D64: South Express | E64: 1213.3 | F64: 51.69 | G64: 486.74 | H64: Cash | I64: 69 | J64: 778.25 | K64: =Table1[[#This Row],[Order_Value]]+Table1[[#This Row],[Delivery_Fee]]-Table1[[#This Row],[Discount]] -> 778.25 | L64: =YEAR(Table1[[#This Row],[Order_Time]]) -> 2023 | M64: =TEXT(Table1[[#This Row],[Order_Time]],"MMM") -> Jan | N64: =HOUR(Table1[[#This Row],[Order_Time]]) -> 14 | O64: =IF(Table1[[#This Row],[Order_Value]]>1000,"High","Low") -> High
A65: ORD100063 | B65: 44929.625 | C65: Bangalore | D65: Pizza Corner | E65: 991.06 | F65: 30.14 | G65: 219.71 | H65: UPI | I65: 56 | J65: 801.4899999999999 | K65: =Table1[[#This Row],[Order_Value]]+Table1[[#This Row],[Delivery_Fee]]-Table1[[#This Row],[Discount]] -> 801.49 | L65: =YEAR(Table1[[#This Row],[Order_Time]]) -> 2023 | M65: =TEXT(Table1[[#This Row],[Order_Time]],"MMM") -> Jan | N65: =HOUR(Table1[[#This Row],[Order_Time]]) -> 15 | O65: =IF(Table1[[#This Row],[Order_Value]]>1000,"High","Low") -> Low
A66: ORD100064 | B66: 44929.667 | C66: Chennai | D66: South Express | E66: 1430.36 | F66: 39.84 | G66: 194.79 | H66: Cash | I66: 11 | J66: 1275.4099999999999 | K66: =Table1[[#This Row],[Order_Value]]+Table1[[#This Row],[Delivery_Fee]]-Table1[[#This Row],[Discount]] -> 1275.41 | L66: =YEAR(Table1[[#This Row],[Order_Time]]) -> 2023 | M66: =TEXT(Table1[[#This Row],[Order_Time]],"MMM") -> Jan | N66: =HOUR(Table1[[#This Row],[Order_Time]]) -> 16 | O66: =IF(Table1[[#This Row],[Order_Value]]>1000,"High","Low") -> High
A67: ORD100065 | B67: 44929.708 | C67: Delhi | D67: Biryani House | E67: 1655.88 | F67: 73.41 | G67: 123.64 | H67: UPI | I67: 32 | J67: 1605.65 | K67: =Table1[[#This Row],[Order_Value]]+Table1[[#This Row],[Delivery_Fee]]-Table1[[#This Row],[Discount]] -> 1605.65 | L67: =YEAR(Table1[[#This Row],[Order_Time]]) -> 2023 | M67: =TEXT(Table1[[#This Row],[Order_Time]],"MMM") -> Jan | N67: =HOUR(Table1[[#This Row],[Order_Time]]) -> 17 | O67: =IF(Table1[[#This Row],[Order_Value]]>1000,"High","Low") -> High
A68: ORD100066 | B68: 44929.75 | C68: Kolkata | D68: Pizza Corner | E68: 161.52 | F68: 63.52 | G68: 493.54 | H68: Cash | I68: 79 | J68: -268.5 | K68: =Table1[[#This Row],[Order_Value]]+Table1[[#This Row],[Delivery_Fee]]-Table1[[#This Row],[Discount]] -> -268.5 | L68: =YEAR(Table1[[#This Row],[Order_Time]]) -> 2023 | M68: =TEXT(Table1[[#This Row],[Order_Time]],"MMM") -> Jan | N68: =HOUR(Table1[[#This Row],[Order_Time]]) -> 18 | O68: =IF(Table1[[#This Row],[Order_Value]]>1000,"High","Low") -> Low
A69: ORD100067 | B69: 44929.792 | C69: Hyderabad | D69: Tandoori Nights | E69: 360.68 | F69: 16.12 | G69: 234.66 | H69: Cash | I69: 20 | J69: 142.14000000000001 | K69: =Table1[[#This Row],[Order_Value]]+Table1[[#This Row],[Delivery_Fee]]-Table1[[#This Row],[Discount]] -> 142.14 | L69: =YEAR(Table1[[#This Row],[Order_Time]]) -> 2023 | M69: =TEXT(Table1[[#This Row],[Order_Time]],"MMM") -> Jan | N69: =HOUR(Table1[[#This Row],[Order_Time]]) -> 19 | O69: =IF(Table1[[#This Row],[Order_Value]]>1000,"High","Low") -> Low
A70: ORD100068 | B70: 44929.833 | C70: Mumbai | D70: Pizza Corner | E70: 187.01 | F70: 76.49 | G70: 470.07 | H70: UPI | I70: 32 | J70: -206.57 | K70: =Table1[[#This Row],[Order_Value]]+Table1[[#This Row],[Delivery_Fee]]-Table1[[#This Row],[Discount]] -> -206.57 | L70: =YEAR(Table1[[#This Row],[Order_Time]]) -> 2023 | M70: =TEXT(Table1[[#This Row],[Order_Time]],"MMM") -> Jan | N70: =HOUR(Table1[[#This Row],[Order_Time]]) -> 20 | O70: =IF(Table1[[#This Row],[Order_Value]]>1000,"High","Low") -> Low
A71: ORD100069 | B71: 44929.875 | C71: Bangalore | D71: Spice Hub | E71: 1149.79 | F71: 6.64 | G71: 339.58 | H71: Wallet | I71: 60 | J71: 816.8500000000001 | K71: =Table1[[#This Row],[Order_Value]]+Table1[[#This Row],[Delivery_Fee]]-Table1[[#This Row],[Discount]] -> 816.85 | L71: =YEAR(Table1[[#This Row],[Order_Time]]) -> 2023 | M71: =TEXT(Table1[[#This Row],[Order_Time]],"MMM") -> Jan | N71: =HOUR(Table1[[#This Row],[Order_Time]]) -> 21 | O71: =IF(Table1[[#This Row],[Order_Value]]>1000,"High","Low") -> High
A72: ORD100070 | B72: 44929.917 | C72: Delhi | D72: Biryani House | E72: 541.99 | F72: 57.06 | G72: 130.25 | H72: Wallet | I72: 23 | J72: 468.79999999999995 | K72: =Table1[[#This Row],[Order_Value]]+Table1[[#This Row],[Delivery_Fee]]-Table1[[#This Row],[Discount]] -> 468.8 | L72: =YEAR(Table1[[#This Row],[Order_Time]]) -> 2023 | M72: =TEXT(Table1[[#This Row],[Order_Time]],"MMM") -> Jan | N72: =HOUR(Table1[[#This Row],[Order_Time]]) -> 22 | O72: =IF(Table1[[#This Row],[Order_Value]]>1000,"High","Low") -> Low
A73: ORD100071 | B73: 44929.958 | C73: Chennai | D73: South Express | E73: 1056.93 | F73: 32.69 | G73: 229.78 | H73: UPI | I73: 65 | J73: 859.8400000000001 | K73: =Table1[[#This Row],[Order_Value]]+Table1[[#This Row],[Delivery_Fee]]-Table1[[#This Row],[Discount]] -> 859.84 | L73: =YEAR(Table1[[#This Row],[Order_Time]]) -> 2023 | M73: =TEXT(Table1[[#This Row],[Order_Time]],"MMM") -> Jan | N73: =HOUR(Table1[[#This Row],[Order_Time]]) -> 23 | O73: =IF(Table1[[#This Row],[Order_Value]]>1000,"High","Low") -> High
A74: ORD100072 | B74: 44930 | C74: Mumbai | D74: Spice Hub | E74: 673.43 | F74: 85.73 | G74: 15.81 | H74: Card | I74: 69 | J74: 743.35 | K74: =Table1[[#This Row],[Order_Value]]+Table1[[#This Row],[Delivery_Fee]]-Table1[[#This Row],[Discount]] -> 743.35 | L74: =YEAR(Table1[[#This Row],[Order_Time]]) -> 2023 | M74: =TEXT(Table1[[#This Row],[Order_Time]],"MMM") -> Jan | N74: =HOUR(Table1[[#This Row],[Order_Time]]) -> 0 | O74: =IF(Table1[[#This Row],[Order_Value]]>1000,"High","Low") -> Low
A75: ORD100073 | B75: 44930.042 | C75: Bangalore | D75: Tandoori Nights | E75: 1384.02 | F75: 71.52 | G75: 5.68 | H75: Wallet | I75: 21 | J75: 1449.86 | K75: =Table1[[#This Row],[Order_Value]]+Table1[[#This Row],[Delivery_Fee]]-Table1[[#This Row],[Discount]] -> 1449.86 | L75: =YEAR(Table1[[#This Row],[Order_Time]]) -> 2023 | M75: =TEXT(Table1[[#This Row],[Order_Time]],"MMM") -> Jan | N75: =HOUR(Table1[[#This Row],[Order_Time]]) -> 1 | O75: =IF(Table1[[#This Row],[Order_Value]]>1000,"High","Low") -> High
A76: ORD100074 | B76: 44930.083 | C76: Bangalore | D76: Spice Hub | E76: 1200.32 | F76: 55.93 | G76: 67.33 | H76: Cash | I76: 67 | J76: 1188.92 | K76: =Table1[[#This Row],[Order_Value]]+Table1[[#This Row],[Delivery_Fee]]-Table1[[#This Row],[Discount]] -> 1188.92 | L76: =YEAR(Table1[[#This Row],[Order_Time]]) -> 2023 | M76: =TEXT(Table1[[#This Row],[Order_Time]],"MMM") -> Jan | N76: =HOUR(Table1[[#This Row],[Order_Time]]) -> 2 | O76: =IF(Table1[[#This Row],[Order_Value]]>1000,"High","Low") -> High
A77: ORD100075 | B77: 44930.125 | C77: Mumbai | D77: Pizza Corner | E77: 1788.7 | F77: 63.44 | G77: 3.45 | H77: Card | I77: 64 | J77: 1848.69 | K77: =Table1[[#This Row],[Order_Value]]+Table1[[#This Row],[Delivery_Fee]]-Table1[[#This Row],[Discount]] -> 1848.69 | L77: =YEAR(Table1[[#This Row],[Order_Time]]) -> 2023 | M77: =TEXT(Table1[[#This Row],[Order_Time]],"MMM") -> Jan | N77: =HOUR(Table1[[#This Row],[Order_Time]]) -> 3 | O77: =IF(Table1[[#This Row],[Order_Value]]>1000,"High","Low") -> High
A78: ORD100076 | B78: 44930.167 | C78: Delhi | D78: Biryani House | E78: 135.82 | F78: 98.08 | G78: 370.83 | H78: Wallet | I78: 47 | J78: -136.93 | K78: =Table1[[#This Row],[Order_Value]]+Table1[[#This Row],[Delivery_Fee]]-Table1[[#This Row],[Discount]] -> -136.93 | L78: =YEAR(Table1[[#This Row],[Order_Time]]) -> 2023 | M78: =TEXT(Table1[[#This Row],[Order_Time]],"MMM") -> Jan | N78: =HOUR(Table1[[#This Row],[Order_Time]]) -> 4 | O78: =IF(Table1[[#This Row],[Order_Value]]>1000,"High","Low") -> Low
A79: ORD100077 | B79: 44930.208 | C79: Pune | D79: Tandoori Nights | E79: 1513.35 | F79: 58.16 | G79: 155.18 | H79: UPI | I79: 49 | J79: 1416.33 | K79: =Table1[[#This Row],[Order_Value]]+Table1[[#This Row],[Delivery_Fee]]-Table1[[#This Row],[Discount]] -> 1416.33 | L79: =YEAR(Table1[[#This Row],[Order_Time]]) -> 2023 | M79: =TEXT(Table1[[#This Row],[Order_Time]],"MMM") -> Jan | N79: =HOUR(Table1[[#This Row],[Order_Time]]) -> 5 | O79: =IF(Table1[[#This Row],[Order_Value]]>1000,"High","Low") -> High
A80: ORD100078 | B80: 44930.25 | C80: Mumbai | D80: Spice Hub | E80: 1888.34 | F80: 5.85 | G80: 145.62 | H80: Cash | I80: 25 | J80: 1748.5699999999997 | K80: =Table1[[#This Row],[Order_Value]]+Table1[[#This Row],[Delivery_Fee]]-Table1[[#This Row],[Discount]] -> 1748.57 | L80: =YEAR(Table1[[#This Row],[Order_Time]]) -> 2023 | M80: =TEXT(Table1[[#This Row],[Order_Time]],"MMM") -> Jan | N80: =HOUR(Table1[[#This Row],[Order_Time]]) -> 6 | O80: =IF(Table1[[#This Row],[Order_Value]]>1000,"High","Low") -> High
A81: ORD100079 | B81: 44930.292 | C81: Hyderabad | D81: Pizza Corner | E81: 1164.04 | F81: 49.11 | G81: 374.68 | H81: UPI | I81: 28 | J81: 838.4699999999998 | K81: =Table1[[#This Row],[Order_Value]]+Table1[[#This Row],[Delivery_Fee]]-Table1[[#This Row],[Discount]] -> 838.47 | L81: =YEAR(Table1[[#This Row],[Order_Time]]) -> 2023 | M81: =TEXT(Table1[[#This Row],[Order_Time]],"MMM") -> Jan | N81: =HOUR(Table1[[#This Row],[Order_Time]]) -> 7 | O81: =IF(Table1[[#This Row],[Order_Value]]>1000,"High","Low") -> High
A82: ORD100080 | B82: 44930.333 | C82: Pune | D82: Urban Tadka | E82: 1268.79 | F82: 24.37 | G82: 242.88 | H82: Wallet | I82: 48 | J82: 1050.2799999999997 | K82: =Table1[[#This Row],[Order_Value]]+Table1[[#This Row],[Delivery_Fee]]-Table1[[#This Row],[Discount]] -> 1050.28 | L82: =YEAR(Table1[[#This Row],[Order_Time]]) -> 2023 | M82: =TEXT(Table1[[#This Row],[Order_Time]],"MMM") -> Jan | N82: =HOUR(Table1[[#This Row],[Order_Time]]) -> 8 | O82: =IF(Table1[[#This Row],[Order_Value]]>1000,"High","Low") -> High
A83: ORD100081 | B83: 44930.375 | C83: Kolkata | D83: Urban Tadka | E83: 1288.65 | F83: 44.81 | G83: 212.07 | H83: Wallet | I83: 50 | J83: 1121.39 | K83: =Table1[[#This Row],[Order_Value]]+Table1[[#This Row],[Delivery_Fee]]-Table1[[#This Row],[Discount]] -> 1121.39 | L83: =YEAR(Table1[[#This Row],[Order_Time]]) -> 2023 | M83: =TEXT(Table1[[#This Row],[Order_Time]],"MMM") -> Jan | N83: =HOUR(Table1[[#This Row],[Order_Time]]) -> 9 | O83: =IF(Table1[[#This Row],[Order_Value]]>1000,"High","Low") -> High
A84: ORD100082 | B84: 44930.417 | C84: Chennai | D84: Urban Tadka | E84: 1041.1 | F84: 14.64 | G84: 35.33 | H84: UPI | I84: 44 | J84: 1020.41 | K84: =Table1[[#This Row],[Order_Value]]+Table1[[#This Row],[Delivery_Fee]]-Table1[[#This Row],[Discount]] -> 1020.41 | L84: =YEAR(Table1[[#This Row],[Order_Time]]) -> 2023 | M84: =TEXT(Table1[[#This Row],[Order_Time]],"MMM") -> Jan | N84: =HOUR(Table1[[#This Row],[Order_Time]]) -> 10 | O84: =IF(Table1[[#This Row],[Order_Value]]>1000,"High","Low") -> High
A85: ORD100083 | B85: 44930.458 | C85: Hyderabad | D85: Biryani House | E85: 0 | F85: 43.31 | G85: 172.09 | H85: UPI | I85: 60 | K85: =Table1[[#This Row],[Order_Value]]+Table1[[#This Row],[Delivery_Fee]]-Table1[[#This Row],[Discount]] -> -128.78 | L85: =YEAR(Table1[[#This Row],[Order_Time]]) -> 2023 | M85: =TEXT(Table1[[#This Row],[Order_Time]],"MMM") -> Jan | N85: =HOUR(Table1[[#This Row],[Order_Time]]) -> 11 | O85: =IF(Table1[[#This Row],[Order_Value]]>1000,"High","Low") -> Low
A86: ORD100084 | B86: 44930.5 | C86: Kolkata | D86: Spice Hub | E86: 1781.62 | F86: 57.48 | G86: 87.67 | H86: Wallet | I86: 20 | J86: 1751.4299999999998 | K86: =Table1[[#This Row],[Order_Value]]+Table1[[#This Row],[Delivery_Fee]]-Table1[[#This Row],[Discount]] -> 1751.43 | L86: =YEAR(Table1[[#This Row],[Order_Time]]) -> 2023 | M86: =TEXT(Table1[[#This Row],[Order_Time]],"MMM") -> Jan | N86: =HOUR(Table1[[#This Row],[Order_Time]]) -> 12 | O86: =IF(Table1[[#This Row],[Order_Value]]>1000,"High","Low") -> High
A87: ORD100085 | B87: 44930.542 | C87: Mumbai | D87: Urban Tadka | E87: 787.18 | F87: 52.06 | G87: 445.83 | H87: UPI | I87: 48 | J87: 393.41 | K87: =Table1[[#This Row],[Order_Value]]+Table1[[#This Row],[Delivery_Fee]]-Table1[[#This Row],[Discount]] -> 393.41 | L87: =YEAR(Table1[[#This Row],[Order_Time]]) -> 2023 | M87: =TEXT(Table1[[#This Row],[Order_Time]],"MMM") -> Jan | N87: =HOUR(Table1[[#This Row],[Order_Time]]) -> 13 | O87: =IF(Table1[[#This Row],[Order_Value]]>1000,"High","Low") -> Low
A88: ORD100086 | B88: 44930.583 | C88: Hyderabad | D88: Tandoori Nights | E88: 1054.9 | F88: 43.11 | G88: 378.68 | H88: Wallet | I88: 13 | J88: 719.3299999999999 | K88: =Table1[[#This Row],[Order_Value]]+Table1[[#This Row],[Delivery_Fee]]-Table1[[#This Row],[Discount]] -> 719.33 | L88: =YEAR(Table1[[#This Row],[Order_Time]]) -> 2023 | M88: =TEXT(Table1[[#This Row],[Order_Time]],"MMM") -> Jan | N88: =HOUR(Table1[[#This Row],[Order_Time]]) -> 14 | O88: =IF(Table1[[#This Row],[Order_Value]]>1000,"High","Low") -> High
A89: ORD100087 | B89: 44930.625 | C89: Pune | D89: South Express | E89: 1481.89 | F89: 43.38 | G89: 465.66 | H89: Wallet | I89: 37 | J89: 1059.6100000000001 | K89: =Table1[[#This Row],[Order_Value]]+Table1[[#This Row],[Delivery_Fee]]-Table1[[#This Row],[Discount]] -> 1059.61 | L89: =YEAR(Table1[[#This Row],[Order_Time]]) -> 2023 | M89: =TEXT(Table1[[#This Row],[Order_Time]],"MMM") -> Jan | N89: =HOUR(Table1[[#This Row],[Order_Time]]) -> 15 | O89: =IF(Table1[[#This Row],[Order_Value]]>1000,"High","Low") -> High
A90: ORD100088 | B90: 44930.667 | C90: Delhi | D90: Biryani House | E90: 252.31 | F90: 94.33 | G90: 297.47 | H90: Card | I90: 35 | J90: 49.16999999999996 | K90: =Table1[[#This Row],[Order_Value]]+Table1[[#This Row],[Delivery_Fee]]-Table1[[#This Row],[Discount]] -> 49.17 | L90: =YEAR(Table1[[#This Row],[Order_Time]]) -> 2023 | M90: =TEXT(Table1[[#This Row],[Order_Time]],"MMM") -> Jan | N90: =HOUR(Table1[[#This Row],[Order_Time]]) -> 16 | O90: =IF(Table1[[#This Row],[Order_Value]]>1000,"High","Low") -> Low
A91: ORD100089 | B91: 44930.708 | C91: Delhi | D91: Tandoori Nights | E91: 862.38 | F91: 31.54 | G91: 450.67 | H91: Cash | I91: 58 | J91: 443.24999999999994 | K91: =Table1[[#This Row],[Order_Value]]+Table1[[#This Row],[Delivery_Fee]]-Table1[[#This Row],[Discount]] -> 443.25 | L91: =YEAR(Table1[[#This Row],[Order_Time]]) -> 2023 | M91: =TEXT(Table1[[#This Row],[Order_Time]],"MMM") -> Jan | N91: =HOUR(Table1[[#This Row],[Order_Time]]) -> 17 | O91: =IF(Table1[[#This Row],[Order_Value]]>1000,"High","Low") -> Low
A92: ORD100090 | B92: 44930.75 | C92: Bangalore | D92: South Express | E92: 140.68 | F92: 4.56 | G92: 398.58 | H92: Card | I92: 36 | J92: -253.34 | K92: =Table1[[#This Row],[Order_Value]]+Table1[[#This Row],[Delivery_Fee]]-Table1[[#This Row],[Discount]] -> -253.34 | L92: =YEAR(Table1[[#This Row],[Order_Time]]) -> 2023 | M92: =TEXT(Table1[[#This Row],[Order_Time]],"MMM") -> Jan | N92: =HOUR(Table1[[#This Row],[Order_Time]]) -> 18 | O92: =IF(Table1[[#This Row],[Order_Value]]>1000,"High","Low") -> Low
A93: ORD100091 | B93: 44930.792 | C93: Bangalore | D93: Biryani House | E93: 271.78 | F93: 27.19 | G93: 81.04 | H93: Cash | I93: 54 | J93: 217.92999999999995 | K93: =Table1[[#This Row],[Order_Value]]+Table1[[#This Row],[Delivery_Fee]]-Table1[[#This Row],[Discount]] -> 217.93 | L93: =YEAR(Table1[[#This Row],[Order_Time]]) -> 2023 | M93: =TEXT(Table1[[#This Row],[Order_Time]],"MMM") -> Jan | N93: =HOUR(Table1[[#This Row],[Order_Time]]) -> 19 | O93: =IF(Table1[[#This Row],[Order_Value]]>1000,"High","Low") -> Low
A94: ORD100092 | B94: 44930.833 | C94: Mumbai | D94: South Express | E94: 440.94 | F94: 96.74 | G94: 218.75 | H94: UPI | I94: 44 | J94: 318.92999999999995 | K94: =Table1[[#This Row],[Order_Value]]+Table1[[#This Row],[Delivery_Fee]]-Table1[[#This Row],[Discount]] -> 318.93 | L94: =YEAR(Table1[[#This Row],[Order_Time]]) -> 2023 | M94: =TEXT(Table1[[#This Row],[Order_Time]],"MMM") -> Jan | N94: =HOUR(Table1[[#This Row],[Order_Time]]) -> 20 | O94: =IF(Table1[[#This Row],[Order_Value]]>1000,"High","Low") -> Low
A95: ORD100093 | B95: 44930.875 | C95: Hyderabad | D95: Spice Hub | E95: 602.4 | F95: 88.02 | G95: 12.61 | H95: Wallet | I95: 34 | J95: 677.81 | K95: =Table1[[#This Row],[Order_Value]]+Table1[[#This Row],[Delivery_Fee]]-Table1[[#This Row],[Discount]] -> 677.81 | L95: =YEAR(Table1[[#This Row],[Order_Time]]) -> 2023 | M95: =TEXT(Table1[[#This Row],[Order_Time]],"MMM") -> Jan | N95: =HOUR(Table1[[#This Row],[Order_Time]]) -> 21 | O95: =IF(Table1[[#This Row],[Order_Value]]>1000,"High","Low") -> Low
A96: ORD100094 | B96: 44930.917 | C96: Chennai | D96: Tandoori Nights | E96: 1695.39 | F96: 21.46 | G96: 214.1 | H96: Cash | I96: 59 | J96: 1502.7500000000002 | K96: =Table1[[#This Row],[Order_Value]]+Table1[[#This Row],[Delivery_Fee]]-Table1[[#This Row],[Discount]] -> 1502.75 | L96: =YEAR(Table1[[#This Row],[Order_Time]]) -> 2023 | M96: =TEXT(Table1[[#This Row],[Order_Time]],"MMM") -> Jan | N96: =HOUR(Table1[[#This Row],[Order_Time]]) -> 22 | O96: =IF(Table1[[#This Row],[Order_Value]]>1000,"High","Low") -> High
A97: ORD100095 | B97: 44930.958 | C97: Bangalore | D97: Tandoori Nights | E97: 1216.42 | F97: 43.9 | G97: 383.08 | H97: Cash | I97: 14 | J97: 877.2400000000002 | K97: =Table1[[#This Row],[Order_Value]]+Table1[[#This Row],[Delivery_Fee]]-Table1[[#This Row],[Discount]] -> 877.24 | L97: =YEAR(Table1[[#This Row],[Order_Time]]) -> 2023 | M97: =TEXT(Table1[[#This Row],[Order_Time]],"MMM") -> Jan | N97: =HOUR(Table1[[#This Row],[Order_Time]]) -> 23 | O97: =IF(Table1[[#This Row],[Order_Value]]>1000,"High","Low") -> High
A98: ORD100096 | B98: 44931 | C98: Pune | D98: Urban Tadka | E98: 576.28 | F98: 74.55 | G98: 268.8 | H98: Card | I98: 51 | J98: 382.0299999999999 | K98: =Table1[[#This Row],[Order_Value]]+Table1[[#This Row],[Delivery_Fee]]-Table1[[#This Row],[Discount]] -> 382.03 | L98: =YEAR(Table1[[#This Row],[Order_Time]]) -> 2023 | M98: =TEXT(Table1[[#This Row],[Order_Time]],"MMM") -> Jan | N98: =HOUR(Table1[[#This Row],[Order_Time]]) -> 0 | O98: =IF(Table1[[#This Row],[Order_Value]]>1000,"High","Low") -> Low
A99: ORD100097 | B99: 44931.042 | C99: Pune | D99: South Express | E99: 1496.37 | F99: 35.54 | G99: 243.35 | H99: Cash | I99: 82 | J99: 1288.56 | K99: =Table1[[#This Row],[Order_Value]]+Table1[[#This Row],[Delivery_Fee]]-Table1[[#This Row],[Discount]] -> 1288.56 | L99: =YEAR(Table1[[#This Row],[Order_Time]]) -> 2023 | M99: =TEXT(Table1[[#This Row],[Order_Time]],"MMM") -> Jan | N99: =HOUR(Table1[[#This Row],[Order_Time]]) -> 1 | O99: =IF(Table1[[#This Row],[Order_Value]]>1000,"High","Low") -> High
A100: ORD100098 | B100: 44931.083 | C100: Delhi | D100: Biryani House | E100: 1022.35 | F100: 77.06 | G100: 487.2 | H100: UPI | I100: 16 | J100: 612.21 | K100: =Table1[[#This Row],[Order_Value]]+Table1[[#This Row],[Delivery_Fee]]-Table1[[#This Row],[Discount]] -> 612.21 | L100: =YEAR(Table1[[#This Row],[Order_Time]]) -> 2023 | M100: =TEXT(Table1[[#This Row],[Order_Time]],"MMM") -> Jan | N100: =HOUR(Table1[[#This Row],[Order_Time]]) -> 2 | O100: =IF(Table1[[#This Row],[Order_Value]]>1000,"High","Low") -> High
...

Sheet KPI_Tracker
A1: KEY PERFORMANCE INDICATOR
A3: KPI Name | D3: Actual Value | G3: Unit
A4: Total Orders | D4: =COUNTA('Cleaned Data'!A:A)-1 -> 5200 | G4: Count
A5: Total Amount | D5: =SUM('Cleaned Data'!K2:K5201) -> 4323690 | G5: ₹
A6: Average Order Value | D6: =AVERAGE('Cleaned Data'!K2:K5201) -> 831.47885 | G6: ₹
A7: Total Discount Given | D7: =SUM('Cleaned Data'!G2:G5201) -> 1290229.4 | G7: ₹
A8: Average Delivery Time | D8: =AVERAGE('Cleaned Data'!I2:I5201) -> 49.416538 | G8: Days

Sheet Dashboard
A1: FOOD DELIVERY PERFORMANCE DASHBOARD
A3: Revenue | Orders | Average Delivery Time | Average Order Value
A4: =KPI_Tracker!D5 -> 4323690 | D4: =KPI_Tracker!D4 -> 5200 | F4: =KPI_Tracker!D8 -> 49.416538 | J4: =KPI_Tracker!D6 -> 831.47885

Sheet Pivot_Analysis
A3: Peak Hours | D3: City Performance | I3: Delivery Performance
A4: Hours | B4: Count | D4: City | E4: Revenue | F4: Orders | G4: Avg Delivery Time | I4: City | J4: Avg Delivery Time | K4: Orders
A5: 15 | B5: 217 | D5: Bangalore | E5: 618231.05 | F5: 755 | G5: 48.468874 | I5: Bangalore | J5: 48.468874 | K5: 755
A6: 0 | B6: 217 | D6: Chennai | E6: 571618.65 | F6: 698 | G6: 48.290831 | I6: Kolkata | J6: 50.090788 | K6: 749
A7: 9 | B7: 217 | D7: Delhi | E7: 636649.48 | F7: 724 | G7: 48.890884 | I7: Pune | J7: 49.218157 | K7: 738
A8: 1 | B8: 217 | D8: Hyderabad | E8: 588137.03 | F8: 725 | G8: 50.398621 | I8: Hyderabad | J8: 50.398621 | K8: 725
A9: 13 | B9: 217 | D9: Kolkata | E9: 609875.7 | F9: 749 | G9: 50.090788 | I9: Delhi | J9: 48.890884 | K9: 724
A10: 2 | B10: 217 | D10: Mumbai | E10: 616596.65 | F10: 707 | G10: 50.161245 | I10: Mumbai | J10: 50.161245 | K10: 707
A11: 8 | B11: 217 | D11: Pune | E11: 596036.39 | F11: 738 | G11: 49.218157 | I11: Chennai | J11: 48.290831 | K11: 698
A12: 3 | B12: 217 | D12: Unknown | E12: 86545.08 | F12: 104 | G12: 52.153846 | I12: Unknown | J12: 52.153846 | K12: 104
A13: 10 | B13: 217 | D13: Grand Total | E13: 4323690 | F13: 5200 | G13: 49.416538 | I13: Grand Total | J13: 49.416538 | K13: 5200
A14: 4 | B14: 217
A15: 12 | B15: 217 | D15: Payment Mode | I15: Order Value / Revenue Analysis
A16: 5 | B16: 217 | D16: Payment Mode | E16: Total Orders | F16: Revenue | I16: Order Category | J16: Orders | K16: Revenue | L16: Avg Discount
A17: 14 | B17: 217 | D17: Wallet | E17: 1332 | F17: 1113066 | I17: High | J17: 2690 | K17: 3514404.1 | L17: 248.11135
A18: 6 | B18: 217 | D18: Cash | E18: 1316 | F18: 1089600.7 | I18: Low | J18: 2510 | K18: 809285.92 | L18: 248.13142
A19: 7 | B19: 217 | D19: UPI | E19: 1277 | F19: 1064231 | I19: Grand Total | J19: 5200 | K19: 4323690 | L19: 248.12104
A20: 11 | B20: 217 | D20: Card | E20: 1275 | F20: 1056792.3
A21: 23 | B21: 216 | D21: Grand Total | E21: 5200 | F21: 4323690
A22: 21 | B22: 216
A23: 20 | B23: 216 | D23: City Revenue | G23: Payment Mode
A24: 17 | B24: 216 | D24: City | E24: Revenue | G24: Payment Mode | H24: Total Orders
A25: 22 | B25: 216 | D25: Bangalore | E25: 618231.05 | G25: Wallet | H25: 1332
A26: 18 | B26: 216 | D26: Chennai | E26: 571618.65 | G26: Cash | H26: 1316
A27: 16 | B27: 216 | D27: Delhi | E27: 636649.48 | G27: UPI | H27: 1277
A28: 19 | B28: 216 | D28: Hyderabad | E28: 588137.03 | G28: Card | H28: 1275
A29: Grand Total | B29: 5200 | D29: Kolkata | E29: 609875.7 | G29: Grand Total | H29: 5200
D30: Mumbai | E30: 616596.65
D31: Pune | E31: 596036.39 | G31: Delivery Performance
D32: Unknown | E32: 86545.08 | G32: City | H32: Avg Delivery Time
D33: Grand Total | E33: 4323690 | G33: Bangalore | H33: 48.468874
G34: Chennai | H34: 48.290831
G35: Delhi | H35: 48.890884
G36: Hyderabad | H36: 50.398621
G37: Kolkata | H37: 50.090788
G38: Mumbai | H38: 50.161245
G39: Pune | H39: 49.218157
G40: Unknown | H40: 52.153846
G41: Grand Total | H41: 49.416538
